yolov3_minimal/__init__.py
yolov3_minimal/models.py
yolov3_minimal/utils.py
yolov3_minimal-0.1.5.dist-info/LICENSE
yolov3_minimal-0.1.5.dist-info/METADATA
yolov3_minimal-0.1.5.dist-info/WHEEL
yolov3_minimal-0.1.5.dist-info/top_level.txt
yolov3_minimal-0.1.5.dist-info/RECORD
